pupyt/__init__.py
pupyt/demo.py
pupyt/helper.py
pupyt/join.py
pupyt/pupyt.py
pupyt/test_pupyt.py
pupyt-0.0.7.dist-info/LICENSE
pupyt-0.0.7.dist-info/METADATA
pupyt-0.0.7.dist-info/WHEEL
pupyt-0.0.7.dist-info/top_level.txt
pupyt-0.0.7.dist-info/RECORD
