Metadata-Version: 2.1
Name: pupyt
Version: 0.0.7
Summary: pure python table
Home-page: https://github.com/Beachnad/pupyt/
Author: Danny Beachnau
Author-email: DannyBeachnau@gmail.com
License: UNKNOWN
Platform: UNKNOWN
Classifier: Programming Language :: Python :: 3
Classifier: License :: OSI Approved :: MIT License
Classifier: Operating System :: OS Independent
